setup.cfg
setup.py
aws_timely.egg-info/PKG-INFO
aws_timely.egg-info/SOURCES.txt
aws_timely.egg-info/dependency_links.txt
aws_timely.egg-info/requires.txt
aws_timely.egg-info/top_level.txt
timely/__init__.py
timely/timely.py