Metadata-Version: 1.1
Name: aws-timely
Version: 0.2.0
Summary: Manage the uptime of Amazon Web Services EC2 containers
Home-page: https://github.com/rightlag/timely
Author: Jason Walsh
Author-email: rightlag@gmail.com
License: MIT
Keywords: aws ec2 uptime
Platform: UNKNOWN
Classifier: Development Status :: 4 - Beta
